{"ID": 1078, "Number": 312, "Title": " Near the Cross", "Author": null, "Key": "F", "Stanzas": 0, "Category": 3, "CategoryName": "SDA Hymnal", "Lyrics": [{"label": "1", "text": "Jesus, keep me near the cross;\nthere a precious fountain,\nfree to all, a healing stream,\nflows from Calvary's mountain."}, {"label": "Refrain", "text": "In the cross, in the cross,\nbe my glory ever,\ntill my raptured soul shall find\nrest beyond the river."}, {"label": "2", "text": "Near the cross, a trembling soul,\nlove and mercy found me;\nthere the bright and morning star\nsheds its beams around me."}, {"label": "3", "text": "Near the cross! O Lamb of God,\nbring its scenes before me;\nhelp me walk from day to day\nwith its shadow o'er me."}, {"label": "4", "text": "Near the cross I'll watch and wait,\nhoping, trusting ever,\ntill I reach the golden strand"}], "Active": 1, "CrossReference": null}