{"ID": 1718, "Number": 266, "Title": " Ô Seigneur", "Author": null, "Key": "", "Stanzas": 0, "Category": 2, "CategoryName": "Hymne et Louange", "Lyrics": [{"label": "1", "text": "Ô Seigneur, ta voix m'appelle!\nPar mon nom tu me connais\nEt mon coeur, longtemps rebelle,\nSe donne à toi pour jamais."}, {"label": "2", "text": "C'est pour toi que je veux vivre,\nCar toi seul est mon berger,\nC'est toi seul que je veux suivre,\nEt non plus un étranger."}, {"label": "3", "text": "N'as-tu pas donné ta vie\nPour me sauver, bon Pasteur?\nGloire à ta grâce infinie!\nGloire à toi, mon Rédempteur!"}, {"label": "4", "text": "Ô mon âme, prends courage!\nJésus marche devant toi,\nEt, jusqu'au bout du voyage,\nSon amour veille sur moi."}, {"label": "5", "text": "Ne crains pas qu'il abandonne\nSa brebis dans le chemin;\nIl est fidèle, et personne\nNe l'ôtera de sa main."}], "Active": 1, "CrossReference": null}