{"ID": 1875, "Number": 423, "Title": " Au seuil de chaque année", "Author": null, "Key": "", "Stanzas": 0, "Category": 2, "CategoryName": "Hymne et Louange", "Lyrics": [{"label": "1", "text": "Au seuil de chaque année\nPar le temps entraînée,\nCantiques et prières\nMontent à Dieu le Père."}, {"label": "2", "text": "Au milieu des alarmes,\nSous la croix, dans les larmes,\nQu'ils nous soit une escorte\nEt nous guide à main forte!"}, {"label": "3", "text": "Et que son soleil luise\nSur la juste entreprise,\nSur le travail austère\nDes humbles de la terre!"}, {"label": "4", "text": "Qu'à tous ceux qui soupirent\nVers la paix qu'ils désirent,\nIl donne patience\nEt vivante espérance!"}, {"label": "5", "text": "Que dans les maladies,\nLes douleurs ennemis,\nNous n'ayons point de crainte :\nDieu règle leur étreinte."}, {"label": "6", "text": "Maître des destinées,\nDes heures, des années,\nPar ta grâce infinie\nDirige notre vie. Amen!"}], "Active": 1, "CrossReference": null}