{"ID": 215, "Number": 85, "Title": "HE NORATRAINA IANAO", "Author": null, "Key": "Eb", "Stanzas": 0, "Category": 1, "CategoryName": "Fihirana Advantista (Malagasy)", "Lyrics": [{"label": "1", "text": "He noratraina Ianao,\nKa nolatsaina, ry Tompo Tsitoha,\nNy dian-kapoka teo Aminao\nNo nanasitranana ny ratrako."}, {"label": "2", "text": "Raha nohomboana Ianao,\nIndro nafoinao, hatolotra ho ahy\nHitarika ny fiainako izao,\nNatolotrao, Jeso ô, ny Fanahy."}, {"label": "3", "text": "Nefa tsy tana Ianao,\nFa indro nitsangana ilay Tompo soa\nResy ny fasana, resy izao,\nO! fandresena nomena ahy koa."}, {"label": "4", "text": "Any an-danitra, Jeso,\n‘Lay Andriamanitra, Tompo Tsitoha.\nIzy mifona ho ahy izao,\nHery sy fanantenana tokoa"}, {"label": "5", "text": "Tsy ho ela intsony re izao,\nAvy eny ambony, ho avy Jeso;\nO! ny hafaliana raha ho avy Ianao,\nHaleloia hitsenako Anao"}], "Active": 1, "CrossReference": null}