{"ID": 2155, "Number": 1, "Title": "J'AIME L'ÉTERNEL", "Author": null, "Key": "", "Stanzas": 0, "Category": 5, "CategoryName": "J'aime l'Eternel (JEM)", "Lyrics": [{"label": "1", "text": "J'aime l'Éternel, car il entend ma voix;\nil a penché son oreille vers moi;\nje l'invoquerai toute ma vie.\nJ'aime l'Éternel, j'aime l'Éternel.\nIl a délivré mon âme de la mort,\nmes yeux des larmes,\nmes pieds de la chute.\nL'Éternel est miséricordieux et juste,\nil est plein de compassion,\nil est plein de compassion."}], "Active": 1, "CrossReference": null}