{"ID": 2333, "Number": 180, "Title": " NOUS CHANTERONS POUR TOI SEIGNEUR", "Author": null, "Key": "", "Stanzas": 0, "Category": 5, "CategoryName": "J'aime l'Eternel (JEM)", "Lyrics": [{"label": "1", "text": "Nous chanterons pour toi Seigneur,\ntu nous fais revivre,\nque ta parole dans nos coeurs\nà jamais nous délivre.\nTu viens, Seigneur, pour rassembler\nles hommes que tu aimes;\nsur les chemins de l'unité\nton amour les ramène.\nTon coeur nous ouvre le festin\ndes noces éternelles,\net nous allons par les chemins\nannoncer la nouvelle.\nLe monde attend de nous, Seigneur,\nun signe de ta gloire,\nque l'Esprit vienne dans nos coeurs\nachever ta victoire.\nGloire éternelle au Dieu vainqueur,\nau maître de l'histoire,\nque l'Esprit chante dans nos coeurs\nsa louange de gloire!"}], "Active": 1, "CrossReference": null}