{"ID": 2530, "Number": 377, "Title": " ALPHA ET OMÉGA", "Author": null, "Key": "", "Stanzas": 0, "Category": 5, "CategoryName": "J'aime l'Eternel (JEM)", "Lyrics": [{"label": "1", "text": "Adrian Snell\nRéjouis-toi! Voici la ville sainte.\nRéjouis-toi! Nouvelle Jérusalem.\nRéjouis-toi! Prépare-toi,\nil vient pour son épouse.\nIl est l'Alpha et l'Oméga,\nle commencement, la fin.\nRéjouis-toi! Voici la ville sainte. (F)\nRéjouis-toi! Nouvelle Jérusalem. (H)\nRéjouis-toi! Prépare-toi,\nil vient pour son épouse.\nIl est l'Alpha et l'Oméga,\nl'Éternel.\nRéjouis-toi! Voici la ville sainte.\nRéjouis-toi! Nouvelle Jérusalem.\nRéjouis-toi! Prépare-toi,\nil vient pour son épouse.\nIl est l'Alpha et l'Oméga,\nle commencement, la fin.\nRéjouis-toi! Voici la ville sainte. (F)\nRéjouis-toi! Nouvelle Jérusalem. (H)\nRéjouis-toi! Prépare-toi,\nil vient pour son épouse.\nIl est l'Alpha et l'Oméga,\nil est vivant.\n(2 x)\nIl est vivant,\nIl est vivant.\n(c) 1986 Word Musik (UK) LTD / CopyCare France\nAdm. pr la langue française LTC, 16 av. de la République, F-94000 Créteil\nUtilisé avec permission\n1 / 2"}], "Active": 1, "CrossReference": null}