{"ID": 2674, "Number": 521, "Title": " AUPRÈS DE DIEU", "Author": null, "Key": "", "Stanzas": 0, "Category": 5, "CategoryName": "J'aime l'Eternel (JEM)", "Lyrics": [{"label": "1", "text": "Charly Siounath\nC'est auprès de Dieu\nque je veux me tenir.\nIl est mon Seigneur, mon Roi.\nC'est auprès de Dieu\nque je peux ressentir,\ntout l'amour qu'il a pour moi.\nC'est auprès de Dieu\nque je voudrais grandir,\nentendre le son de sa voix.\nJe viens, je viens devant le trône,\npar ta grâce je me tiens en ta présence.\nJe lève les yeux vers le lieu saint,\npour contempler ta face,\nje veux rester près de toi.\n(c) 1993 Charly et Isabelle Siounath\nUtilisé avec permission\n1 / 1"}], "Active": 1, "CrossReference": null}