{"ID": 2688, "Number": 535, "Title": " LA TROMPETTE SONNE", "Author": null, "Key": "", "Stanzas": 0, "Category": 5, "CategoryName": "J'aime l'Eternel (JEM)", "Lyrics": [{"label": "1", "text": "Corinne Lafitte\nLa trompette sonne sur notre pays,\nrassemblez-vous mes enfants.\nLa trompette sonne sur notre pays,\nrassemblez-vous pour prier ensemble,\npour chercher ma face, implorer ma grâce,\nélever mon nom, recevoir mes dons.\nUnissez-vous, unissez-vous,\nmon Esprit viendra sur vous.\nLa trompette sonne sur notre pays,\npréparez-vous mes enfants.\nLa trompette sonne sur notre pays,\nle Roi des rois établit son règne,\nil prend possession de la terre entière,\nbrise les nations d'un sceptre de fer.\nPurifiez-vous, purifiez-vous,\ncar le feu viendra sur vous.\nLa trompette sonne sur notre pays,\nréveillez-vous mes enfants.\nLa trompette sonne sur notre pays,\nréveillez-vous car voici l'Epoux.\nLe repas des noces vous est préparé,\ndes couronnes d'or vous sont réservées.\nRéjouissez-vous, réjouissez-vous,\ncar le Roi revient pour vous.\n(c) 1994 Corinne Lafitte\nUtilisé avec permission\n1 / 2"}], "Active": 1, "CrossReference": null}