{"ID": 2787, "Number": 634, "Title": " LENT À LA COLÈRE", "Author": null, "Key": "", "Stanzas": 0, "Category": 5, "CategoryName": "J'aime l'Eternel (JEM)", "Lyrics": [{"label": "1", "text": "Elisabeth Bourbouze\nO Seigneur, tu es un Dieu de grâce, (2 x)\ndont l'amour à jamais nous dépasse, (2 x)\nLent à la colère et riche en bonté. (2 x)\nTu effaces notre condamnation, (2 x)\nseul Sauveur et Dieu de compassion. (2 x)\nLent à la colère et riche en bonté. (2 x)\nTu déploies ta bannière sur nous. (2 x)\nÉternel, tu es un Dieu jaloux. (2 x)\nLent à la colère et riche en bonté. (2 x)\nTu demeures fidèle à ton alliance, (2 x)\nnotre Dieu rempli de bienveillance. (2 x)\nLent à la colère et riche en bonté. (2 x)\n(c) 1997 Elisabeth Bourbouze\nAdministré par LTC - 16, av. de la République, F-94000 Créteil\nUtilisé avec permission\n1 / 1"}], "Active": 1, "CrossReference": null}