{"ID": 2874, "Number": 722, "Title": " ADMIRABLE EST TON CONSEIL", "Author": null, "Key": "", "Stanzas": 0, "Category": 5, "CategoryName": "J'aime l'Eternel (JEM)", "Lyrics": [{"label": "1", "text": "Sylvain Freymond\nAdmirable est ton conseil,\nsi grande est ta sagesse;\ntu sièges dans les hauteurs,\nau-dessus de l'univers.\nQue tes actions sont grandioses\net tes pensées profondes!\nTu es le Dieu tout-puissant,\ninfiniment grand.\nDans mon esprit, ton nom me remplit:\nPère éternel, roi bienveillant, Dieu qui entends,\ntoi seul es l'Éternel Dieu,\nSeigneur et maître des cieux.\nTu es parfait dans tous tes aspects: fidélité,\nmiséricorde, justice et paix,\npatience, immense bonté,\nSauveur de l'humanité.\n(c) 2003 Sylvain Freymond. Utilisé avec permission.\n1 / 1"}], "Active": 1, "CrossReference": null}