{"ID": 2958, "Number": 806, "Title": " O DIEU MON ROC", "Author": null, "Key": "", "Stanzas": 0, "Category": 5, "CategoryName": "J'aime l'Eternel (JEM)", "Lyrics": [{"label": "1", "text": "Linda Panci-Mc Gowen et Rolf Schneider\nO Dieu, mon roc, mon refuge et ma force,\nune tour solide en face de l'ennemi,\ndans la tempête, tu étends sur moi tes ailes.\nJe veux chanter, car tu es mon bouclier.\nEntends mon cri, ô Dieu, entends mon cri.\nDu bout de la terre, je t'appelle au secours.\nLe monde bascule, tous mes repères s'en vont.\nDu bout de la terre, je crie vers toi, mon Dieu.\nJe viens vers toi quand je suis abattu.\nDu fond de mon cœur s'élève ma prière.\nIl n 'y a qu'en toi que je retrouve l'espoir.\nDu fond de mon cœur je me confie en toi.\n(c) 2003 Linda Panci-McGowen et Rolf Schneider\n1 / 1"}], "Active": 1, "CrossReference": null}