{"ID": 3283, "Number": 129, "Title": "Any naraina,ilay avotr'aina", "Author": "N.F.S Grundvig", "Key": "", "Stanzas": 0, "Category": 6, "CategoryName": "Fihirana Fanampiny (FFPM)", "Lyrics": [{"label": "1", "text": "1. Any naraina\n:,: Ilay Avotr'aina. :,:\nNatsangan-dRay.\nResy ny ota,\n:,: ka ny mpanota, :,:\nMihoby indray.\nAny naraina...\n2. Hira hiraina\n:,: Ny Tompon'aina :,:\nIsaoranay;\nOry ny fony\n:,: mba hampitony:,:\nNy sentonay.\nHira hiraina...\n3. Faly ny very,\n:,: tsy manan-kery :,:\nNy helokay;\nJesosy Tompo\n:,: dia mampanompo :,:\nNy rafinay.\nFaly ny very...\n4. Hisy maraina\n:,: ny Tompon'aina :,:\nHo avy indray;\nIzy hizara\n:,: ny lova tsara :,:\nHomena anay.\nHisy maraina..."}], "Active": 1, "CrossReference": ""}