{"ID": 3365, "Number": 211, "Title": "Ilay Boky izay nodorana", "Author": "Ratovondrahety Rahihavanana 1919", "Key": "", "Stanzas": 0, "Category": 6, "CategoryName": "Fihirana Fanampiny (FFPM)", "Lyrics": [{"label": "1", "text": "1. Ilay Boky 'zay nodorana,\nDia may nefa tsy levona;\nIzay natao ho lavenona,\nLasa vato fanorenana;\nNoheverina ho foana\nKanjo mainka koa velona;\n'Lay nafenina, nalevina,\nNo nisandratra nivelatra!\nIza moa no hahasakana,\nEny, Iza no hanohitra,\nIlay teny voasoratra,\nDia ny Tenin'Andriamanitra\nZao rehetr'izao ho levona\nFa ny Teny no haharitra.\n2. Rasalama nolefonina,\nNisy hafa koa nodorana.\nHantsana no namarinana,\nTora-bato: fahafatesana\nDia tao ireo nampinomina,\nNoterena mba hiozona:\nMoa izany nampivadika\nKristiana be finoana?\nValin-teny voasoratra\nNentiny nandresy lahatra:\nFeo tony, tava mirana,\nFeno hery, hasambarana:\n\"Tsy mba misy hatahorako\nAfa-tsy Hianao ry Tompoko\"\n3. Ilay teny masina sy to\nManambara ry Mpamonjiko\nTena saro-bidy ao am-po,\nKa vakiko sy iainako\nFifaliako, fiarovako,\nFahazavana ao an-dalako;\nKoa tanako ho lovako\nSy isaorako ny Tompoko,\nMaty aho nefa velona,\nFa Kristy no ahavelomako.\nMaty Izy nohomboana\nNoho ny fahotana vitako\nNefa Izy dia nitsangana\nSantatry ny hitsanganako."}], "Active": 1, "CrossReference": ""}