{"ID": 3417, "Number": 263, "Title": "Mandrenesa ry sofina", "Author": "Maintimolaly", "Key": "", "Stanzas": 0, "Category": 6, "CategoryName": "Fihirana Fanampiny (FFPM)", "Lyrics": [{"label": "1", "text": "1. Mandrenesa ry sofina\nMifalia, ry fo\nNy feon'ny Filazantsara\nManatona anao\n2. Ry olon'ota rehetra\nRy ory sy noana\nIzay mameno ny kibony\nAmin-java-poana\n3. Jehovah no mamboatra\nIzay mofon'aina\nHo an'izay rehetra\nMety hihinana\n4. Kristy sy ny fitahiany\nIzany mofo izany\nFa izy no mamelona\nNy maty mosary\n5. Avia, ry mosarena\nKa manaràna fo\nNy mofon'aina tsy lany\nFa ampy ho anao!"}], "Active": 1, "CrossReference": ""}