{"ID": 3459, "Number": 305, "Title": "O, miasa, sakaiza", "Author": "Annie L.Walker Coghill 1839 1907", "Key": "", "Stanzas": 0, "Category": 6, "CategoryName": "Fihirana Fanampiny (FFPM)", "Lyrics": [{"label": "1", "text": "1. O! miasà, sakaiza,\nJeso no herinao;\nNa misy mafy aza,\nIzy tsy handao.\nDia matokia tokoa,\nFa Jeso momba anao.\nKa hisy voka-tsoa\nHifalianao.\n2. Maro ny andro lasa\nlzay tsy nanaovanao,\nKa mbola be ny asa\nlzay tsy vitanao,\nKoa dia mitsangàna\nHanao tokoa izao,\nHahavitanao tsara\nNy anjaranao.\n3. lndro, fa mihariva,\nFohy ny andronao;\nMoa tsy mba fantatrao va\nKa tsy hitanao?\nEny, fa manakaiky\nJeso Mpitsara re,\nAry efa 'mby akaiky\nNy hodianao.\n4. Rehefa tonga Jeso,\nTompon'ny asanao,\nAry hamaly soa\nNy mpiasany.\nMandrakizay doria\nNo hifalianao,\nRaha mpanompo tsara\nMahatoky e!"}], "Active": 1, "CrossReference": ""}