{"ID": 3572, "Number": 418, "Title": "Amorony fo madio", "Author": "Ph.Razafindraraoty 1908 1983", "Key": "", "Stanzas": 0, "Category": 6, "CategoryName": "Fihirana Fanampiny (FFPM)", "Lyrics": [{"label": "1", "text": "1. Amorony fo madio\nAho ry Jehovah ô!\nKa havaozinao anio\nNy fanahiko izao.\nBe ny ratsy vitako,\nKa ny heloko sasao;\nMamindrà fo amiko,\nRy Jehovah Tompo ô!\n2. Amorony fo madio\nAho ry Jehovah ô!\nKa diovy ankehitrio\nNy fiainako izao\nSimba ny fanahiko,\nKa amboary ho vaovao;\nAza esorina amiko\nNy fanahy Masinao.\n3. Amorony fo madio\nAho, ry Jehovah ô!\nKa ny foko ahitsio,\nHamasino ho Anao.\nTaminao dia taminao\nNo Mba nanotàko, Ray;\nKa ny heloko avelao,\nNy fanahiko ovay.\n4. Amorony fo madio\nAho, ry Jehovah ô!\nKa ny fo omeko anio,\nRaiso ho fanananao:\nFo mangorakoraka\nNoho ny ratsy izay natao;\nFo miaiky heloka,\nKa mba raiso, Tompo ô!"}], "Active": 1, "CrossReference": ""}