{"ID": 3594, "Number": 440, "Title": "Ry Kristy ô, Mpanjakako!", "Author": "J.Ralaikera", "Key": "", "Stanzas": 0, "Category": 6, "CategoryName": "Fihirana Fanampiny (FFPM)", "Lyrics": [{"label": "1", "text": "1. Ry Kristy ô, Mpanjakako!\nNy foko ho Anao,\nNy feoko hasandratro\nHihira ho Anao.\n2. Mba raiso ny fanahiko\nHanao ny sitrakao;\nNy tenako, ny heriko,\nDia ento ho Anao.\n3. Ny tongotro, ny tanako,\nHiasa ho Anao;\nny androko, ny volako,\nOmeko ho Anao.\n4. Izaho dia tsy mendrika\nAnao, ry Tompo ô!\nKanefa re, mba raisonao\nNy foko ho Anao."}], "Active": 1, "CrossReference": ""}