{"ID": 3651, "Number": 497, "Title": "Ny tany sy ny lanitra tsy manam petra", "Author": "Hira allemand", "Key": "", "Stanzas": 0, "Category": 6, "CategoryName": "Fihirana Fanampiny (FFPM)", "Lyrics": [{"label": "1", "text": "1. Ny tany sy ny lanitra tsy manampetra\nHiaraka amin'ny mino rehetra,\nManaiky fa Jeso no aina hamonjy\nNy olona ory izay mila vonjy.\n2. Na dia manenjika ahy ny ratsy\nTsy lany ny hery, fa Jeso mamatsy,\nDia Izy na tanako mafy tokoa,\nKa tsy ialako fa Tompo Tsitoha.\n3. Jesosy sakaizako dia miahy\nNy Azy, ka afaka ny ahiahy,\nNy fo malahelo ovany ho faly,\nKa tretrika indray ireo olo-mijaly.\n4. Jesosy fidiko ho Tompo tokoa,\nEfaiko ny asa sy hevitra soa,\nIzay halan'ny Tompo tsy tiako intsony,\nKa tena iraisako tsara ny fony.\n5. Izay tanako mafy sy mamy hambara\nRehefa ho faty, ka ao ny anjara\nJesosy, jesosy irery ihany\nNo aina, harena tsy mety ho lany."}], "Active": 1, "CrossReference": ""}