{"ID": 3706, "Number": 552, "Title": "Ry foko ô, mba atolory", "Author": "G. Neumarck 1621 1681", "Key": "", "Stanzas": 0, "Category": 6, "CategoryName": "Fihirana Fanampiny (FFPM)", "Lyrics": [{"label": "1", "text": "1. Ry foko ô, mba atolory\nNy Rainao ny manjo anao ;\nNa mafy aza ny mahory,\nDia hovonjeny Hianao;\nNy lanitra no andrandrao\nHahafaka ny sentonao.\n2. Andriamanitra mahita\nlzay hahasambatra anao,\nKa Izy no mahay mamita\nlzay zava-tsarotra aminao ;\nTsy hotsitsiny aminao\nlzay mety hahasoa anao.\n3. Ka aza kivy, ry mahantra,\nNa ory aza hianao,\nFa matokia ny Mpiantra,\nIzay tsy mahafoy anao;\nNy amboariny izao\nDia famonjena ho anao.\n4. Dia aoka hianao hatoky,\nRaha mafy ny manjo anao,\nNy Rainao dia mahatoky,\nKa ampy hiankinanao;\nTsy misy tsy ho afany,\nRaha avy ny fotoany"}], "Active": 1, "CrossReference": ""}