{"ID": 3818, "Number": 664, "Title": "Nalain'ny Mpahary ity zaza ity", "Author": "Stef Ramaka", "Key": "", "Stanzas": 0, "Category": 6, "CategoryName": "Fihirana Fanampiny (FFPM)", "Lyrics": [{"label": "1", "text": "1. Nalain'ny Mpahary ity zaza ity\nHo sambatra mandrakizay.\nMiandry antsika nilaozany aty,\nFa mbola hihaona indray.\nFiv : Onony ny fonao, ry mana-manjo,\nAo an-danitra izy izao,\nRavo izy izao,\nFa ny lapan'ny Ray\nFonenana mandrakizay.\n2. Nafahana amin'ny loza ety\nKa tretrika izy izao,\nNy nofo ho lo no alevina aty\nFa any ny tena vaovao.\nOnony ny fo, sns..."}], "Active": 1, "CrossReference": ""}