{"ID": 3849, "Number": 695, "Title": "Ary an", "Author": "H.W. Baker 1821 1877", "Key": "", "Stanzas": 0, "Category": 6, "CategoryName": "Fihirana Fanampiny (FFPM)", "Lyrics": [{"label": "1", "text": "1. Ary an-koatra ary,\nIlay Paradisa soa\nToa takona aty,\nKanefa ao tokoa,\nMamirapiratra ao,\nNy endriky ny Ray;\nJesosy Tompo ao\nMiandry mba handray.\n2. Tsy misy ny hanjo\nIzay tafiditra ao;\nNy ranomaso koa\nTsy afaka hankao\nNy hazavana soa\nManelatrelatra ao;\nNy zava-mahasoa\nTsy misy izay tsy ao.\n3. Anjely marobe\nMihira any koa;\nIreo olo-masina e\nMifaly avokoa.\nAndeha re izao,\nSakaiza marobe,\nAria ny tahotrao,\nKa dia mizora re!\n4. Raha misy loza ety,\nJereo ny Tomponao;\nFa Izy raha tety\nNitondra toy izao.\nIreo fahoriana aty\nOdio tsy hita re,\nHandraisantsika ary\nNy fiadanam-be."}], "Active": 1, "CrossReference": ""}