{"ID": 3865, "Number": 711, "Title": "Tompo o, endrey ny fitahiana", "Author": "Randrianjafy Antsirabe", "Key": "", "Stanzas": 0, "Category": 6, "CategoryName": "Fihirana Fanampiny (FFPM)", "Lyrics": [{"label": "1", "text": "1. Tompo ô, endrey ny fitahiana\nIzay natodrakao ny zanakao.\nVory eto, feno fifaliana,\nAmpoky ny fahasoavanao.\nIzay rehetra nikelezan'aina\nDia nomban'ny fitantananao;\nVonona avokoa izay nilaina,\nTsy mba lany ny harenanao\n2. Indro tranonovitaina\nHanasoavana taranaka,\nHitaizàna, hanolokoloana\nIreo tanora halain-tahaka.\nIzay voafafy, antenaina\nMba hamokatra tsy tapaka;\nDia ho vanona ny firenena,\nKa hitombo, hisandrahaka\n3. Izany re, ry Tompo, no finoana\nTananay, ka mba herezonao\nIzahay handroso tsy hivaona\nEo ambany fiarovanao.\nKa ny fangataham-pitahiana,\nTompo ô! Akarina aminao\nNy Anaranao no iaingàna.\nHoderaina ny Anaranao!"}], "Active": 1, "CrossReference": ""}