{"ID": 3880, "Number": 726, "Title": "Efa hariva Jeso tia!", "Author": "R.G Hartley 1836 1870", "Key": "", "Stanzas": 0, "Category": 6, "CategoryName": "Fihirana Fanampiny (FFPM)", "Lyrics": [{"label": "1", "text": "1. Efa hariva Jeso tia!\nTomoera aminay;\nNy fanahinay tahio,\nFa hatory izahay.\n2. Fa ny helokay ekenay,\nMahavonjy Hianao;\nNy manjo anay lazainay,\nFa miantra ny fonao,\n3. Alina maharitra ela,\nAizi-mampivadi-po,\nFa ny olona fidinao\nTsy mba takona aminao.\n4. Hianao no mitahiry\nNy miankina aminao\nVoahididin'ny anjely\nNy mialoka aminao.\n5. Raha anio no tapitra andro\nIzahay mpanomponao,\nAoka izahay hifoha\nAo an-dapaso anao."}], "Active": 1, "CrossReference": ""}