{"ID": 3938, "Number": 784, "Title": "Jeso be fitia!", "Author": "T. Rowlands 1852 1921", "Key": "", "Stanzas": 0, "Category": 6, "CategoryName": "Fihirana Fanampiny (FFPM)", "Lyrics": [{"label": "1", "text": "1. Jeso be fitia!\nZaza izahay,\nAvy mitaraina\nMihainoa anay.\n2. Bodo sy adala,\nIndreo ny zanakao-,\njeso ô, malala!\nAza lavinao.\n3. Mpiandry ondry mora!\nMba tarihonao;\nTano tsy hania\nNy ondrikelinao.\n4.Aza avela hitady\nLaza aman-jo!\nFa Hianao irery\nNo mahafa-po.\n5.Tianao ny zaza,\njeso! fantatray,\nKa manolo-tena\nHo Anao izahay.\n6.jeso be fitia\nZaza izahay,\nAvy mba hidera;\nMihainoa anay."}], "Active": 1, "CrossReference": ""}