{"ID": 4085, "Number": 91, "Title": "Ami, sois fidèle", "Author": null, "Key": "", "Stanzas": 0, "Category": 7, "CategoryName": "Donnez-Lui gloire", "Lyrics": [{"label": "1", "text": "Ami, sois fidèle!\nJésus vient bientôt\nQui te donnera le repos.\nAvec vigilance poursuis ton combat,\nTiens fermement ce que tu as.\nAmi, sois fidèle!\nFidèle à Celui\nQui a pour toi donné sa vie,\nLe Seigneur qui est, qui était et qui vient,\nQui te veut au milieu des siens."}, {"label": "2", "text": "Ami, sois fidèle!\nSaisi par Jésus,\nAvance tout droit vers le but.\nDevant toi la porte bientôt s’ouvrira,\nTon Sauveur te libérera.\nAmi, sois fidèle!\nCar voici ton roi\nQui te fait entrer dans sa joie!\nEt tu pourras vivre, citoyen des cieux,\nPour toujours dans l’amour de Dieu."}], "Active": 1, "CrossReference": null}