{"ID": 670, "Number": 539, "Title": "HE! MIPOSAKA AO AM-PO ", "Author": null, "Key": "Ab", "Stanzas": 0, "Category": 1, "CategoryName": "Fihirana Advantista (Malagasy)", "Lyrics": [{"label": "1", "text": "He! Miposaka ao am-po, Jesosy\nNy fitiavanao anay.\nEfa narovanao fatratra\nKa tratra ny maraina vao"}, {"label": "ref", "text": "He! Faly re (’zahay)\n’Zahay zanakao (anio)\nMiampy iray (indray)\nNy taonanay (anio);\nOmeo fo hendry sy fivoarana\nHo taona vao ho Anao Jeso"}, {"label": "2", "text": "Ka ny fialiana\nMitoetra ao anatinay izao\nDia entinay hidera ny\nAnaranao mandrakizay."}, {"label": "3", "text": "Ianao Jeso mahay\nMandahatra ny andro iainanay\nKa ny sisa mbola homenao\nHahaizanay hanoa tokoa."}], "Active": 1, "CrossReference": null}